besser/__init__.py
besser/agent/__init__.py
besser/agent/core/__init__.py
besser/agent/core/agent.py
besser/agent/core/file.py
besser/agent/core/message.py
besser/agent/core/property.py
besser/agent/core/session.py
besser/agent/core/state.py
besser/agent/core/entity/__init__.py
besser/agent/core/entity/entity.py
besser/agent/core/entity/entity_entry.py
besser/agent/core/intent/__init__.py
besser/agent/core/intent/intent.py
besser/agent/core/intent/intent_parameter.py
besser/agent/core/processors/__init__.py
besser/agent/core/processors/audio_language_detection_processor.py
besser/agent/core/processors/language_detection_processor.py
besser/agent/core/processors/processor.py
besser/agent/core/processors/user_adaptation_processor.py
besser/agent/core/transition/__init__.py
besser/agent/core/transition/condition.py
besser/agent/core/transition/event.py
besser/agent/core/transition/transition.py
besser/agent/core/transition/transition_builder.py
besser/agent/db/__init__.py
besser/agent/db/monitoring_db.py
besser/agent/db/monitoring_ui/__init__.py
besser/agent/db/monitoring_ui/db_connection.py
besser/agent/db/monitoring_ui/flow_graph.py
besser/agent/db/monitoring_ui/home.py
besser/agent/db/monitoring_ui/intent_details.py
besser/agent/db/monitoring_ui/monitoring_ui.py
besser/agent/db/monitoring_ui/sidebar.py
besser/agent/db/monitoring_ui/table_overview.py
besser/agent/db/monitoring_ui/utils.py
besser/agent/exceptions/__init__.py
besser/agent/exceptions/exceptions.py
besser/agent/exceptions/logger.py
besser/agent/library/__init__.py
besser/agent/library/coroutine/__init__.py
besser/agent/library/coroutine/async_helpers.py
besser/agent/library/entity/__init__.py
besser/agent/library/entity/base_entities.py
besser/agent/library/intent/__init__.py
besser/agent/library/intent/intent_library.py
besser/agent/library/state/__init__.py
besser/agent/library/state/state_library.py
besser/agent/library/transition/__init__.py
besser/agent/library/transition/condition_functions.py
besser_agentic_framework-4.2.3.dist-info/licenses/LICENSE
besser_agentic_framework-4.2.3.dist-info/METADATA
besser_agentic_framework-4.2.3.dist-info/WHEEL
besser_agentic_framework-4.2.3.dist-info/top_level.txt
besser_agentic_framework-4.2.3.dist-info/RECORD
