Metadata-Version: 2.4
Name: besser-agentic-framework
Version: 4.2.3
Summary: BESSER Agentic Framework (BAF)
Author: Luxembourg Institute of Science and Technology
License: MIT
Project-URL: Documentation, https://besser-agentic-framework.readthedocs.io/
Project-URL: Source Code, https://github.com/BESSER-PEARL/BESSER-Agentic-Framework
Project-URL: Bug Tracker, https://github.com/BESSER-PEARL/BESSER-Agentic-Framework/issues
Keywords: agent,bot,framework,chatbot,state-machine,nlp
Requires-Python: >=3.10
License-File: LICENSE
Requires-Dist: aiohttp==3.11.12
Requires-Dist: gidgethub==5.3.0
Requires-Dist: gidgetlab==2.1.0
Requires-Dist: dateparser==1.1.8
Requires-Dist: langdetect==1.0.9
Requires-Dist: nltk==3.9.1
Requires-Dist: numpy==1.26.4
Requires-Dist: pandas==2.3.3
Requires-Dist: python-telegram-bot==21.0
Requires-Dist: psycopg2-binary>=2.9.10
Requires-Dist: pydantic==2.11.7
Requires-Dist: pyvis==0.3.2
Requires-Dist: requests==2.31.0
Requires-Dist: snowballstemmer==2.2.0
Requires-Dist: sqlalchemy==2.0.29
Requires-Dist: streamlit==1.40.0
Requires-Dist: streamlit-antd-components==0.3.2
Requires-Dist: text2num==2.5.0
Requires-Dist: websocket-client==1.6.4
Requires-Dist: websockets==11.0.3
Requires-Dist: bcrypt==4.0.1
Provides-Extra: extras
Requires-Dist: spacy==3.7.2; extra == "extras"
Requires-Dist: scikit-learn>=1.7.0; extra == "extras"
Requires-Dist: librosa==0.10.1; extra == "extras"
Requires-Dist: SpeechRecognition==3.10.0; extra == "extras"
Requires-Dist: soundfile==0.13.1; extra == "extras"
Requires-Dist: opencv-python==4.10.0.84; extra == "extras"
Requires-Dist: plotly==5.18.0; extra == "extras"
Requires-Dist: chromadb==0.5.4; extra == "extras"
Requires-Dist: langchain==0.2.9; extra == "extras"
Requires-Dist: langchain-community==0.2.7; extra == "extras"
Requires-Dist: pypdf==4.3.1; extra == "extras"
Requires-Dist: tiktoken==0.9.0; extra == "extras"
Provides-Extra: llms
Requires-Dist: openai==1.93.0; extra == "llms"
Requires-Dist: replicate==0.23.1; extra == "llms"
Requires-Dist: transformers==4.53.0; extra == "llms"
Provides-Extra: tensorflow
Requires-Dist: keras==3.12.0; extra == "tensorflow"
Requires-Dist: tensorflow==2.20.0; extra == "tensorflow"
Provides-Extra: torch
Requires-Dist: torch==2.5.1; extra == "torch"
Requires-Dist: scikit-learn>=1.7.0; extra == "torch"
Provides-Extra: docs
Requires-Dist: sphinx==7.2.3; extra == "docs"
Requires-Dist: sphinx-copybutton==0.5.2; extra == "docs"
Requires-Dist: sphinx-paramlinks==0.6.0; extra == "docs"
Requires-Dist: furo==2023.8.19; extra == "docs"
Requires-Dist: m2r2==0.3.3; extra == "docs"
Provides-Extra: all
Requires-Dist: spacy==3.7.2; extra == "all"
Requires-Dist: scikit-learn>=1.7.0; extra == "all"
Requires-Dist: librosa==0.10.1; extra == "all"
Requires-Dist: SpeechRecognition==3.10.0; extra == "all"
Requires-Dist: soundfile==0.13.1; extra == "all"
Requires-Dist: opencv-python==4.10.0.84; extra == "all"
Requires-Dist: plotly==5.18.0; extra == "all"
Requires-Dist: chromadb==0.5.4; extra == "all"
Requires-Dist: langchain==0.2.9; extra == "all"
Requires-Dist: langchain-community==0.2.7; extra == "all"
Requires-Dist: pypdf==4.3.1; extra == "all"
Requires-Dist: tiktoken==0.9.0; extra == "all"
Requires-Dist: openai==1.93.0; extra == "all"
Requires-Dist: replicate==0.23.1; extra == "all"
Requires-Dist: transformers==4.53.0; extra == "all"
Requires-Dist: keras==3.12.0; extra == "all"
Requires-Dist: tensorflow==2.20.0; extra == "all"
Requires-Dist: torch==2.5.1; extra == "all"
Requires-Dist: scikit-learn>=1.7.0; extra == "all"
Dynamic: license-file
Dynamic: provides-extra
Dynamic: requires-dist
